popodds/__init__.py
popodds/detection.py
popodds/popodds.py
popodds-0.7.1.dist-info/LICENSE
popodds-0.7.1.dist-info/METADATA
popodds-0.7.1.dist-info/WHEEL
popodds-0.7.1.dist-info/top_level.txt
popodds-0.7.1.dist-info/RECORD
