Metadata-Version: 2.1
Name: popodds
Version: 0.7.1
Summary: Simple package for Bayesian model comparison.
Home-page: https://github.com/mdmould/popodds
Author: Matthew Mould
Author-email: mattdmould@gmail.com
License: MIT
Requires-Python: >=3.7
License-File: LICENSE
Requires-Dist: numpy
Requires-Dist: scipy
Requires-Dist: kaydee
